odoo/addons/payment_acquirer_multi_pms_properties/README.rst
odoo/addons/payment_acquirer_multi_pms_properties/__init__.py
odoo/addons/payment_acquirer_multi_pms_properties/__manifest__.py
odoo/addons/payment_acquirer_multi_pms_properties/controllers/__init__.py
odoo/addons/payment_acquirer_multi_pms_properties/controllers/portal.py
odoo/addons/payment_acquirer_multi_pms_properties/i18n/payment_acquirer_multi_pms_properties.pot
odoo/addons/payment_acquirer_multi_pms_properties/models/__init__.py
odoo/addons/payment_acquirer_multi_pms_properties/models/payment_acquirer.py
odoo/addons/payment_acquirer_multi_pms_properties/readme/CONTRIBUTORS.rst
odoo/addons/payment_acquirer_multi_pms_properties/readme/DESCRIPTION.rst
odoo/addons/payment_acquirer_multi_pms_properties/readme/USAGE.rst
odoo/addons/payment_acquirer_multi_pms_properties/static/description/icon.png
odoo/addons/payment_acquirer_multi_pms_properties/static/description/index.html
odoo/addons/payment_acquirer_multi_pms_properties/views/payment_acquirer.xml
odoo14_addon_payment_acquirer_multi_pms_properties-14.0.1.0.2.dist-info/METADATA
odoo14_addon_payment_acquirer_multi_pms_properties-14.0.1.0.2.dist-info/WHEEL
odoo14_addon_payment_acquirer_multi_pms_properties-14.0.1.0.2.dist-info/top_level.txt
odoo14_addon_payment_acquirer_multi_pms_properties-14.0.1.0.2.dist-info/RECORD
